universal_silabs_flasher/__init__.py
universal_silabs_flasher/__main__.py
universal_silabs_flasher/common.py
universal_silabs_flasher/const.py
universal_silabs_flasher/cpc.py
universal_silabs_flasher/cpc_types.py
universal_silabs_flasher/emberznet.py
universal_silabs_flasher/firmware.py
universal_silabs_flasher/flash.py
universal_silabs_flasher/flasher.py
universal_silabs_flasher/gecko_bootloader.py
universal_silabs_flasher/gpio.py
universal_silabs_flasher/router.py
universal_silabs_flasher/spinel.py
universal_silabs_flasher/spinel_types.py
universal_silabs_flasher-0.1.3.dist-info/licenses/LICENSE
universal_silabs_flasher-0.1.3.dist-info/METADATA
universal_silabs_flasher-0.1.3.dist-info/WHEEL
universal_silabs_flasher-0.1.3.dist-info/entry_points.txt
universal_silabs_flasher-0.1.3.dist-info/top_level.txt
universal_silabs_flasher-0.1.3.dist-info/RECORD
