Metadata-Version: 2.4
Name: universal-silabs-flasher
Version: 0.1.3
Summary: Tool to flash firmware onto any Silicon Labs radio running EmberZNet, CPC multi-PAN, or just a bare Gecko Bootloader
Author-email: Puddly <puddly3@gmail.com>
License: GPL-3.0
Project-URL: repository, https://github.com/NabuCasa/universal-silabs-flasher
Requires-Python: >=3.9
License-File: LICENSE
Requires-Dist: aiohttp
Requires-Dist: click>=8.2.0
Requires-Dist: zigpy>=0.70.0
Requires-Dist: crc
Requires-Dist: bellows>=0.42.0
Requires-Dist: gpiod; platform_system == "Linux"
Requires-Dist: coloredlogs
Requires-Dist: async-timeout; python_version < "3.11"
Requires-Dist: typing_extensions
Requires-Dist: pyserial-asyncio-fast
Provides-Extra: testing
Requires-Dist: pytest>=7.3.1; extra == "testing"
Requires-Dist: pytest-asyncio>=0.21.0; extra == "testing"
Requires-Dist: pytest-timeout>=2.1.0; extra == "testing"
Requires-Dist: pytest-mock>=3.10.0; extra == "testing"
Requires-Dist: pytest-cov>=4.1.0; extra == "testing"
Requires-Dist: pytest-github-actions-annotate-failures; extra == "testing"
Dynamic: license-file
